imptools
