Metadata-Version: 2.1
Name: imptools
Version: 1.3.0
Summary: Tools for improving Python imports.
Home-page: http://github.com/danijar/imptools
Author: Danijar Hafner
Author-email: mail@danijar.com
License: UNKNOWN
Platform: UNKNOWN
Classifier: License :: OSI Approved :: MIT License
Classifier: Programming Language :: Python :: 3
